[
  {
    "label": "RF+SHAP baseline",
    "tracking_error_pct": 3.6313,
    "info_ratio": 1.7803,
    "alpha_annual_pct": 6.4647,
    "total_return_pct": 10.83,
    "index_total_return_pct": 7.33,
    "max_drawdown_pct": -8.87,
    "sharpe": 1.4836,
    "beta": 0.9828
  },
  {
    "label": "Hybrid v1 (SHAP+Influence)",
    "tracking_error_pct": 5.9895,
    "info_ratio": 1.8249,
    "alpha_annual_pct": 10.9305,
    "total_return_pct": 13.05,
    "index_total_return_pct": 7.33,
    "max_drawdown_pct": -10.12,
    "sharpe": 1.4702,
    "beta": 1.176
  },
  {
    "label": "Hybrid v2 (SHAP+EmbSHAP+Infl)",
    "tracking_error_pct": 3.7419,
    "info_ratio": 0.2562,
    "alpha_annual_pct": 0.9587,
    "total_return_pct": 7.75,
    "index_total_return_pct": 7.33,
    "max_drawdown_pct": -9.23,
    "sharpe": 1.0387,
    "beta": 1.05
  }
]